iran_mobile_va/__init__.py
iran_mobile_va/mobile.py
iran_mobiles-0.0.2.dist-info/LICENSE
iran_mobiles-0.0.2.dist-info/METADATA
iran_mobiles-0.0.2.dist-info/WHEEL
iran_mobiles-0.0.2.dist-info/top_level.txt
iran_mobiles-0.0.2.dist-info/RECORD
