Metadata-Version: 2.1
Name: iran-mobiles
Version: 0.0.2
Summary: small package to check if input number is valid iranian cell phone number and its additional information
Home-page: https://github.com/hooman-the1/iran_mobile.git
Author: Hooman M.
Author-email: hooman.the110@gmail.com
License: UNKNOWN
Platform: UNKNOWN
Classifier: Programming Language :: Python :: 3
Classifier: License :: OSI Approved :: MIT License
Classifier: Operating System :: OS Independent
Requires-Python: >=3.6
License-File: LICENSE
